{
    "list": [
        {
            "prefab": {
                "instanceID": 22306
            },
            "position": {
                "x": 610.0001831054688,
                "y": 1095.5970458984375,
                "z": 17.30130386352539
            }
        },
        {
            "prefab": {
                "instanceID": 22344
            },
            "position": {
                "x": 690.9817504882813,
                "y": 1044.2545166015625,
                "z": 18.999998092651368
            }
        },
        {
            "prefab": {
                "instanceID": 22306
            },
            "position": {
                "x": 613.6128540039063,
                "y": 834.9684448242188,
                "z": 17.30130386352539
            }
        },
        {
            "prefab": {
                "instanceID": 22344
            },
            "position": {
                "x": 427.30755615234377,
                "y": 885.8758544921875,
                "z": 18.999998092651368
            }
        },
        {
            "prefab": {
                "instanceID": 22344
            },
            "position": {
                "x": 424.2618103027344,
                "y": 1086.8948974609375,
                "z": 18.999998092651368
            }
        },
        {
            "prefab": {
                "instanceID": 22368
            },
            "position": {
                "x": 272.4097900390625,
                "y": 1055.132080078125,
                "z": 19.999998092651368
            }
        }
    ]
}